inventree_test_statistics-0.1.3.dist-info/licenses/LICENSE
test_statistics/__init__.py
test_statistics/core.py
test_statistics/serializers.py
test_statistics/version.py
test_statistics/views.py
test_statistics/static/TestStatisticsPanel.js
inventree_test_statistics-0.1.3.dist-info/METADATA
inventree_test_statistics-0.1.3.dist-info/WHEEL
inventree_test_statistics-0.1.3.dist-info/entry_points.txt
inventree_test_statistics-0.1.3.dist-info/top_level.txt
inventree_test_statistics-0.1.3.dist-info/RECORD
