Metadata-Version: 2.4
Name: inventree-test-statistics
Version: 0.1.3
Summary: Test statistics plugin for InvenTree
Home-page: https://github.com/inventree/inventree-test-statistics
Author: Oliver Walters
Author-email: oliver.henry.walters@gmail.com
License: MIT
Keywords: inventree inventory
Classifier: Programming Language :: Python :: 3
Classifier: Operating System :: OS Independent
Classifier: Framework :: InvenTree
Requires-Python: >=3.9
License-File: LICENSE
Requires-Dist: tablib
Dynamic: author
Dynamic: author-email
Dynamic: classifier
Dynamic: description
Dynamic: description-content-type
Dynamic: home-page
Dynamic: keywords
Dynamic: license
Dynamic: license-file
Dynamic: requires-dist
Dynamic: requires-python
Dynamic: summary
